pkgrig/__init__.py
pkgrig-0.0.0a0.dist-info/licenses/LICENSE
pkgrig-0.0.0a0.dist-info/METADATA
pkgrig-0.0.0a0.dist-info/WHEEL
pkgrig-0.0.0a0.dist-info/top_level.txt
pkgrig-0.0.0a0.dist-info/RECORD
