Metadata-Version: 2.4
Name: pkgrig
Version: 0.0.0a0
Summary: Generates production-ready Python applications with a built-in scaffolding for optimized binaries, secure containers, and cloud-native CI/CD pipelines.
Author-email: "mesotron.dev" <mail@mesotron.dev>
Maintainer-email: "mesotron.dev" <mail@mesotron.dev>
License:                                  Apache License
Project-URL: Homepage, https://github.com/nortosem/pkgrig
Project-URL: Repository, https://github.com/nortosem/pkgrig
Keywords: package,template,scaffold,cookiecutter,jinja2,nuitka,compiler,container,podman,docker,gcp,google-cloud-build,cloudbuild,ci/cd,devops
Classifier: Development Status :: 2 - Pre-Alpha
Classifier: Environment :: Console
Classifier: Intended Audience :: Developers
Classifier: License :: OSI Approved :: Apache Software License
Classifier: Programming Language :: Python :: 3
Classifier: Topic :: Software Development :: Build Tools
Classifier: Topic :: Software Development :: Code Generators
Classifier: Topic :: System :: Software Distribution
Requires-Python: >=3.13
License-File: LICENSE
Requires-Dist: click>=8.0
Requires-Dist: Jinja2>=3.1
Requires-Dist: tomli>=2.0
Requires-Dist: tomli-w>=1.0
Provides-Extra: dev
Requires-Dist: devrig>=0.0.0a0; extra == "dev"
Dynamic: license-file
